akparse/__init__.py
akparse/parsers.py
akparse/consts/__init__.py
akparse/consts/ak_constants.py
akparse/errs/__init__.py
akparse/errs/ak_error.py
akparse/utils/__init__.py
akparse/utils/ak_echo.py
akparse-0.1.8.dist-info/LICENSE
akparse-0.1.8.dist-info/METADATA
akparse-0.1.8.dist-info/WHEEL
akparse-0.1.8.dist-info/top_level.txt
akparse-0.1.8.dist-info/RECORD
