Metadata-Version: 2.1
Name: akparse
Version: 0.1.8
Summary: A args parse package with -,--,,|,{,},[,],= and character patterns.
Home-page: https://github.com/absentm/akparse
Author: AbsentM
Author-email: absentm@163.com
License: UNKNOWN
Project-URL: Bug Tracker, https://github.com/absentm/akparse/issues
Platform: UNKNOWN
Classifier: Programming Language :: Python :: 2
Classifier: Programming Language :: Python :: 3
Classifier: License :: OSI Approved :: MIT License
Classifier: Operating System :: OS Independent
Requires-Python: >=2.6
